MANIFEST.in
Makefile
README.md
README.rst
requirements.txt
runtests.py
setup.py
Shake_Files.egg-info/PKG-INFO
Shake_Files.egg-info/SOURCES.txt
Shake_Files.egg-info/dependency_links.txt
Shake_Files.egg-info/not-zip-safe
Shake_Files.egg-info/requires.txt
Shake_Files.egg-info/top_level.txt
shake_files/__init__.py
shake_files/utils.py
tests/__init__.py
tests/test_core.py